setup.py
md_test_package/Binomialdistribution.py
md_test_package/Gaussiandistribution.py
md_test_package/Generaldistribution.py
md_test_package/__init__.py
md_test_package.egg-info/PKG-INFO
md_test_package.egg-info/SOURCES.txt
md_test_package.egg-info/dependency_links.txt
md_test_package.egg-info/not-zip-safe
md_test_package.egg-info/top_level.txt